skolmaten/__init__.py
skolmaten/skolmaten.py
skolmaten_python-1.0.0.dist-info/LICENSE.md
skolmaten_python-1.0.0.dist-info/METADATA
skolmaten_python-1.0.0.dist-info/WHEEL
skolmaten_python-1.0.0.dist-info/top_level.txt
skolmaten_python-1.0.0.dist-info/RECORD
