Metadata-Version: 2.1
Name: skolmaten-python
Version: 1.0.0
Summary: An python wrapper for the skolmaten service.
Home-page: https://github.com/simoncircle/skolmaten-python
Author: Simon Lövskog
Author-email: simon@lovskog.eu
License: MIT
Platform: UNKNOWN
Classifier: Programming Language :: Python :: 3
Classifier: License :: OSI Approved :: MIT License
Classifier: Operating System :: OS Independent
Requires-Dist: requests
Requires-Dist: xmltodict
